{
    "comment": {
        "content": "追求刺激的人，没有永远的高潮，前一分钟意气风发，后一分钟郁郁寡欢。",
        "color_scheme": {
            "is_dark": true,
            "primary_color_light": "726651",
            "secondary_color": "f9f8f4",
            "primary_color_dark": "4c4436"
        },
        "source": "",
        "poster": "https://img2.doubanio.com/view/photo/l/public/p2580140982.jpg"
    },
    "ad": {},
    "today": {
        "date": "2020-11-13",
        "description": "",
        "title": ""
    },
    "subject": {
        "rating": {
            "count": 49122,
            "max": 10,
            "star_count": 4,
            "value": 7.9
        },
        "pubdate": [
            "2000-12-22(美国)"
        ],
        "pic": {
            "large": "https://img1.doubanio.com/view/photo/m_ratio_poster/public/p794606009.jpg",
            "normal": "https://img1.doubanio.com/view/photo/s_ratio_poster/public/p794606009.jpg"
        },
        "is_show": false,
        "year": "2000",
        "card_subtitle": "2000 / 英国 法国 美国 / 喜剧 犯罪 冒险\n乔尔·科恩 / 伊桑·科恩 导演",
        "id": "1292264",
        "genres": [
            "喜剧",
            "犯罪",
            "冒险"
        ],
        "title": "逃狱三王",
        "is_released": true,
        "actors": [
            {
                "name": "乔治·克鲁尼"
            },
            {
                "name": "约翰·特托罗"
            },
            {
                "name": "蒂姆·布雷克·尼尔森"
            },
            {
                "name": "约翰·古德曼"
            },
            {
                "name": "霍利·亨特"
            },
            {
                "name": "Chris Thomas King"
            },
            {
                "name": "查尔斯·德恩"
            },
            {
                "name": "Del Pentecost"
            },
            {
                "name": "迈克尔·巴达鲁科"
            },
            {
                "name": "韦恩·杜瓦尔"
            },
            {
                "name": "艾迪·盖尔"
            },
            {
                "name": "雷·迈克金农"
            },
            {
                "name": "丹尼尔·冯·巴根"
            },
            {
                "name": "罗伊斯·D.阿普勒加特"
            },
            {
                "name": "弗兰克·考利森"
            },
            {
                "name": "李韦弗"
            },
            {
                "name": "斯蒂芬·鲁特"
            },
            {
                "name": "吉莉恩·韦尔奇"
            },
            {
                "name": "Mia Tate"
            },
            {
                "name": "穆赛塔·万德"
            },
            {
                "name": "Christy Taylor"
            },
            {
                "name": "Michael W. Finnell"
            },
            {
                "name": "约翰·麦康奈尔"
            },
            {
                "name": "Ryder Davis"
            },
            {
                "name": "Jerry Douglas"
            },
            {
                "name": "Christopher Francis"
            },
            {
                "name": "杰弗里·古尔德"
            },
            {
                "name": "纳撒尼尔·李·JR"
            }
        ],
        "color_scheme": {
            "is_dark": true,
            "primary_color_light": "a59a6c",
            "_base_color": [
                0.13380281690140844,
                0.3480392156862745,
                0.8
            ],
            "secondary_color": "f9f8f4",
            "_avg_color": [
                0.12893081761006286,
                0.31927710843373497,
                0.6509803921568628
            ],
            "primary_color_dark": "7f7653"
        },
        "type": "movie",
        "has_linewatch": true,
        "cover_url": "https://img1.doubanio.com/view/photo/m_ratio_poster/public/p794606009.jpg",
        "sharing_url": "https://www.douban.com/doubanapp/dispatch/movie/1292264",
        "url": "https://movie.douban.com/subject/1292264/",
        "release_date": null,
        "uri": "douban://douban.com/movie/1292264",
        "subtype": "movie",
        "directors": [
            {
                "name": "乔尔·科恩"
            },
            {
                "name": "伊桑·科恩"
            }
        ],
        "null_rating_reason": ""
    }
}